setup.py
bin/yaml_extract
bin/yaml_get
bin/yaml_merge
bin/yaml_prune
bin/yaml_put
bin/yaml_rename
bin/yaml_transform
bin/yaml_validate
bin/yaml_walk
yaml_utilities/__init__.py
yaml_utilities.egg-info/PKG-INFO
yaml_utilities.egg-info/SOURCES.txt
yaml_utilities.egg-info/dependency_links.txt
yaml_utilities.egg-info/not-zip-safe
yaml_utilities.egg-info/requires.txt
yaml_utilities.egg-info/top_level.txt