Metadata-Version: 1.0
Name: yaml-utilities
Version: 0.1
Summary: YAML utilities
Home-page: http://github.com/emayssat/yaml_utilities
Author: Emmanuel Mayssat
Author-email: emmanuel.mayssat@aya.yale.edu
License: MIT
Platform: UNKNOWN
